Topsis_Vaibhav_102003711/Topsis_Vaibhav_102003711.py
Topsis_Vaibhav_102003711/__init__.py
Topsis_Vaibhav_102003711-0.0.1.dist-info/METADATA
Topsis_Vaibhav_102003711-0.0.1.dist-info/WHEEL
Topsis_Vaibhav_102003711-0.0.1.dist-info/top_level.txt
Topsis_Vaibhav_102003711-0.0.1.dist-info/RECORD
