Metadata-Version: 2.1
Name: Topsis-Vaibhav-102003711
Version: 0.0.1
Summary: This is a Python Package implementing TOPSIS used for multi-criteria decision analysis method
Author: Vaibhav
Author-email: vvaibhav_be20@thapar.edu
License: MIT
Keywords: topsis,mcda,UCS654,TIET
Classifier: Development Status :: 3 - Alpha
Classifier: Intended Audience :: Developers
Classifier: Topic :: Software Development :: Build Tools
Classifier: License :: OSI Approved :: MIT License
Requires-Dist: numpy
Requires-Dist: pandas
